.gitignore
.readthedocs.yml
CHANGES.rst
MANIFEST.in
README.rst
pyproject.toml
setup.cfg
setup.py
tox.ini
.github/workflows/tex-tests.yml
docs/M101_Nucleus_irs.png
docs/Makefile
docs/background.rst
docs/conf.py
docs/file_formats.rst
docs/fit_spectrum.rst
docs/index.rst
docs/install.rst
docs/make.bat
docs/plot_result.rst
docs/requirements.txt
docs/_templates/autosummary/base.rst
docs/_templates/autosummary/class.rst
docs/_templates/autosummary/module.rst
docs/idl_vs_python/NGC2023_pixel_14_18.png
docs/idl_vs_python/NGC2023_pixel_21_37.png
docs/idl_vs_python/python_vs_IDL_fit.rst
licenses/LICENSE.rst
pahfit/PAHFIT_Spitzer_Exgal.py
pahfit/__init__.py
pahfit/_astropy_init.py
pahfit/base.py
pahfit/component_models.py
pahfit/conftest.py
pahfit/feature_strengths.py
pahfit/helpers.py
pahfit/version.py
pahfit.egg-info/PKG-INFO
pahfit.egg-info/SOURCES.txt
pahfit.egg-info/dependency_links.txt
pahfit.egg-info/entry_points.txt
pahfit.egg-info/not-zip-safe
pahfit.egg-info/requires.txt
pahfit.egg-info/top_level.txt
pahfit/data/1120229.txt
pahfit/data/1C_snr_gt20.ecsv
pahfit/data/M101_Nucleus_irs.ipac
pahfit/data/M101_Nucleus_irs_IDL-PAHFIT-result.xdr
pahfit/data/Orion_H2S1_ISO-SWS_merged.ipac
pahfit/data/Orion_H2S1_ISO-SWS_original.ipac
pahfit/data/Orion_H2S1_merged-vs-original.ps
pahfit/data/README.rst
pahfit/data/orion_bar_SWS_with7023shape.ipac
pahfit/packs/scipack_ExGal_SpitzerIRSSLLL.ipac
pahfit/packs/scipack_classic.yml
pahfit/packs/scipack_general.yml
pahfit/scripts/__init__.py
pahfit/scripts/plot_pahfit.py
pahfit/scripts/run_pahfit.py
pahfit/tests/__init__.py
pahfit/tests/coveragerc
pahfit/tests/test_classic_pack.py
pahfit/tests/test_fitting_spitzer.py
pahfit/utils/__init__.py
pahfit/utils/tests/__init__.py