Metadata-Version: 2.1
Name: pahfit
Version: 2.0
Summary: fit the features in near- and mid-IR astronomical spectra
Home-page: https://pahfit.readthedocs.io
Author: PAHFIT developers
Author-email: kgordon@stsci.edu
License: GNU GPL v3+
Platform: UNKNOWN
Requires-Python: >=3.6
Provides-Extra: test
Provides-Extra: docs
License-File: licenses/LICENSE.rst
